{
    "name":  "production-saas-readiness-inventory",
    "type":  "object",
    "requiredFields":  [
                           "version",
                           "lastReviewedDate",
                           "areas",
                           "p5Roadmap",
                           "nonClaims"
                       ],
    "areaRequiredFields":  [
                               "area",
                               "currentStatus",
                               "evidence",
                               "risk",
                               "recommendedAction"
                           ],
    "roadmapRequiredFields":  [
                                  "item",
                                  "title",
                                  "status",
                                  "risk"
                              ],
    "allowedRoadmapItems":  [
                                "P5-01",
                                "P5-02",
                                "P5-03",
                                "P5-04",
                                "P5-05",
                                "P5-06",
                                "P5-07",
                                "P5-08",
                                "P5-09",
                                "P5-10",
                                "P5-11",
                                "P5-12",
                                "P5-13",
                                "P5-14",
                                "P5-15",
                                "P5-16A",
                                "P5-16B",
                                "P5-16C",
                                "P5-16D",
                                "P5-17",
                                "P6-00",
                                "P6-01",
                                "P6-02",
                                "P6-03",
                                "P6-04",
                                "P6-05",
                                "P6-06",
                                "P6-07",
                                "P6-08",
                                "P6-09",
                                "P6-10",
                                "P6-11",
                                "P6-12",
                                "P6-13",
                                "P6-14",
                                "P6-15",
                                "P7-00",
                                "P7-01",
                                "P7-02",
                                "P7-03",
                                "P7-04",
                                "P7-05",
                                "P7-06",
                                "P7-07",
                                "P7-08"
                            ],
    "statusNotes":  {
                        "planned":  "Planned work item for staged P5 rollout.",
                        "unknownNeedsAudit":  "Use UnknownNeedsAudit when evidence is incomplete."
                    },
    "allowedRoadmapStatuses":  [
                                   "Implemented",
                                   "AuditOnly",
                                   "DesignOnly",
                                   "StrategyOnly",
                                   "GovernanceOnly",
                                   "ToolingOnly",
                                   "TestOnly",
                                   "DisabledBoundary",
                                   "Reference",
                                   "Template",
                                   "NeedsCleanup",
                                   "Superseded"
                               ]
}
