{
    "code":  200,
    "msg":  null,
    "data":  {
                 "total":  1,
                 "data":  [
                              {
                                  "operatorId":  null,
                                  "operator":  null,
                                  "operatorLoginId":  null,
                                  "operation":  null,
                                  "operationTime":  null,
                                  "id":  1014,
                                  "scope":  1,
                                  "nameCn":  "J4 GMV",
                                  "nameEn":  "J4 GMV",
                                  "descriptionCn":  "",
                                  "descriptionEn":  "",
                                  "createdBy":  null,
                                  "userCreated":  "å´è³æ\u0085§(å½é\u0085ç®¡çé¨)",
                                  "userModified":  "å´è³æ\u0085§(å½é\u0085ç®¡çé¨)",
                                  "gmtCreated":  "2021-03-20 06:13:35",
                                  "gmtModified":  "2022-08-18 15:50:14",
                                  "delFlag":  0,
                                  "videoList":  null,
                                  "imageList":  [
                                                    {
                                                        "id":  502,
                                                        "dataId":  1014,
                                                        "type":  2,
                                                        "descriptionCn":  null,
                                                        "descriptionEn":  null,
                                                        "filename":  "J4 GMV.PNG",
                                                        "documentSize":  305808,
                                                        "fileKey":  "fb3493fe7d0f468da4cc22cd3246cded.PNG",
                                                        "url":  "https://gree-overseas-prod.s3.ap-southeast-1.amazonaws.com/data-storage/fb3493fe7d0f468da4cc22cd3246cded.PNG?response-content-disposition=inline%3Bfilename%3DJ4%2520GMV.PNG\u0026X-Amz-Algorithm=AWS4-HMAC-SHA256\u0026X-Amz-Date=20260625T102730Z\u0026X-Amz-SignedHeaders=host\u0026X-Amz-Expires=180\u0026X-Amz-Credential=AKIA24UVFLZ5K6WRSD6A%2F20260625%2Fap-southeast-1%2Fs3%2Faws4_request\u0026X-Amz-Signature=6fc9be54b7a253de362ac2e53d59c647cedad0f14c9d002392b39f33c7890b7b"
                                                    }
                                                ],
                                  "fileList":  null,
                                  "fileKey":  null,
                                  "fileName":  null
                              }
                          ]
             }
}
