{
    "repoRoot":  "D:\\Project\\AssistantEngineer",
    "apiBase":  "https://support.gree.com:9877/api",
    "clientUuid":  "b45034f2-e32d-4c4b-924c-a95583a71443",
    "firstSymbols":  [
                         "C"
                     ],
    "maxSecondSymbolsPerFirst":  3,
    "maxCodes":  19,
    "maxModelsPerCode":  1,
    "downloadFiles":  true,
    "maxDownloads":  45,
    "allowPresignFallback":  false,
    "maxRequests":  180,
    "delaySeconds":  45,
    "jitterSeconds":  20,
    "onlyCodes":  [
                      "H0",
                      "H1",
                      "H2",
                      "H3",
                      "H4",
                      "H6",
                      "H7",
                      "H8",
                      "H9",
                      "HA",
                      "HC",
                      "HE",
                      "HF",
                      "HH",
                      "HJ",
                      "HL",
                      "Ho",
                      "HP",
                      "HU"
                  ],
    "onlyModels":  [
                       "GMV"
                   ],
    "planOnly":  false,
    "startedUtc":  "2026-06-25T08:49:00.0533889Z"
}
